fsm-assignments/problem3_vending/vending_mealy.v
module vending_mealy(
    input wire clk,
    input wire rst, // sync active-high
    input wire [1:0] coin, // 01=5, 10=10, 00=idle
    output wire dispense,// 1-cycle pulse
    output wire chg5 // 1-cycle pulse when returning 5
);

    reg [1:0] state_present, state_next;

    parameter init = 2'b00;
    parameter s5 = 2'b01;
    parameter s10 = 2'b10;
    parameter s15 = 2'b11;

    reg dispense_reg, chg5_reg;
    assign dispense = dispense_reg;
    assign chg5 = chg5_reg;

    always @ (posedge clk) begin
        if(rst) state_present <= init;
        else state_present <= state_next;
    end

    always @ (*) begin

        // default values
        state_next = state_present;
        dispense_reg=0;
        chg5_reg=0;
        
        case(state_present) 

            init: begin
                if(coin==2'b01) state_next = s5;
                else if(coin==2'b10) state_next = s10;
            end
            
            s5: begin
                if(coin==2'b01) state_next = s10;
                else if(coin==2'b10) state_next = s15;
            end

            s10: begin
                if(coin==2'b01) state_next = s15;
                else if(coin==2'b10) begin
                    state_next = init;
                    dispense_reg=1;
                end
            end

            s15: begin
                if(coin==2'b01) begin
                    state_next = init;
                    dispense_reg=1;
                end
                else if(coin==2'b10) begin
                    state_next = init;
                    dispense_reg=1;
                    chg5_reg=1;
                end
            end

            default: begin
                state_next = init;
            end

        endcase
    end

    // assign dispense = ( ( state_present == s15 ) || (state_present == s10 && coin==2'b10) );
    // assign chg5 = ( state_present ==s15 && coin==2'b10 );


endmodule

fsm-assignments/problem3_vending/tb_vending_mealy.v
`include "vending_mealy.v"
`timescale 1ns/1ps

module tb_vending_mealy;

    reg clk;
    reg rst;
    reg [1:0] coin;
    wire dispense;
    wire chg5;

    vending_mealy dut (
        .clk(clk),
        .rst(rst),
        .coin(coin),
        .dispense(dispense),
        .chg5(chg5)
    );

    // Clock generation (10ns period)
    always #5 clk = ~clk;

    initial begin
        $dumpfile("dump.vcd");
        $dumpvars(0, tb_vending_mealy);

        clk = 0;
        rst = 1;
        coin = 2'b00;

        // Hold reset
        #10;
        rst = 0;

        // Insert 5, 5, 10 => total = 20 => dispense
        #10 coin = 2'b01; // insert 5
        #10 coin = 2'b01; // insert 5
        #10 coin = 2'b10; // insert 10
        #10 coin = 2'b00; // idle

        // Insert 10, 10 => total = 20 => dispense
        #10 coin = 2'b10; // insert 10
        #10 coin = 2'b10; // insert 10
        #10 coin = 2'b00;

        // Insert 10, 5, 10 => total = 25 => dispense + change
        #10 coin = 2'b10; // insert 10
        #10 coin = 2'b01; // insert 5
        #10 coin = 2'b10; // insert 10
        #10 coin = 2'b00;

        // Finish
        #50 $finish;
    end

endmodule

fsm-assignments/problem3_vending/dump.vcd
$date
	Tue Aug 19 14:05:25 2025
$end
$version
	Icarus Verilog
$end
$timescale
	1ps
$end
$scope module tb_vending_mealy $end
$var wire 1 ! dispense $end
$var wire 1 " chg5 $end
$var reg 1 # clk $end
$var reg 2 $ coin [1:0] $end
$var reg 1 % rst $end
$scope module dut $end
$var wire 1 " chg5 $end
$var wire 1 # clk $end
$var wire 2 & coin [1:0] $end
$var wire 1 ! dispense $end
$var wire 1 % rst $end
$var parameter 2 ' init $end
$var parameter 2 ( s10 $end
$var parameter 2 ) s15 $end
$var parameter 2 * s5 $end
$var reg 1 + chg5_reg $end
$var reg 1 , dispense_reg $end
$var reg 2 - state_next [1:0] $end
$var reg 2 . state_present [1:0] $end
$upscope $end
$upscope $end
$enddefinitions $end
$comment Show the parameter values. $end
$dumpall
b1 *
b11 )
b10 (
b0 '
$end
#0
$dumpvars
bx .
b0 -
0,
0+
b0 &
1%
b0 $
0#
0"
0!
$end
#5000
b0 .
1#
#10000
0#
0%
#15000
1#
#20000
b1 -
0#
b1 $
b1 &
#25000
b10 -
b1 .
1#
#30000
0#
#35000
b11 -
b10 .
1#
#40000
1!
1,
b0 -
0#
b10 $
b10 &
#45000
b10 -
0!
0,
b0 .
1#
#50000
b0 -
0#
b0 $
b0 &
#55000
1#
#60000
b10 -
0#
b10 $
b10 &
#65000
1!
1,
b0 -
b10 .
1#
#70000
0#
#75000
b10 -
0!
0,
b0 .
1#
#80000
b0 -
0#
b0 $
b0 &
#85000
1#
#90000
b10 -
0#
b10 $
b10 &
#95000
1!
1,
b0 -
b10 .
1#
#100000
0!
0,
b11 -
0#
b1 $
b1 &
#105000
1!
1,
b0 -
b11 .
1#
#110000
1"
1+
1!
1,
b0 -
0#
b10 $
b10 &
#115000
b10 -
0"
0+
0!
0,
b0 .
1#
#120000
b0 -
0#
b0 $
b0 &
