fsm-assignments/problem1_seqdet/seq_detect_mealy.v
module seq_detect_mealy(
    input wire clk,
    input wire rst,   // sync active-high
    input wire din,   // serial input bit per clock
    output wire y     // 1-cycle pulse when pattern ...1101 seen
);
    reg [1:0] state_present, state_next;

    parameter init = 2'b00;
    parameter s1 = 2'b01;
    parameter s2 = 2'b10;
    parameter s3 = 2'b11;

    always @ (posedge clk) begin
        if(rst) state_present <= init;
        else state_present <= state_next;
    end
    
    always @ (*) begin
        case(state_present) 

            init: begin
                if(din) state_next = s1;
                else state_next = init;
            end
            
            s1: begin
                if(din) state_next = s2;
                else state_next = init;
            end

            s2: begin
                if(din) state_next = s2;
                else state_next = s3;
            end

            s3: begin
                if(din) state_next = s1;
                else state_next = init;
            end

            default: begin
                state_next = init;
            end

        endcase
    end

    assign y = (state_present == s3 && din == 1'b1);
            
endmodule

fsm-assignments/problem1_seqdet/tb_seq_detect_mealy.v
`include "seq_detect_mealy.v"
`timescale 1ns/1ns

module tb_seq_detect_mealy;
    reg clk, rst, din;
    wire y;

    seq_detect_mealy dut(
        .clk(clk), 
        .rst(rst), 
        .din(din), 
        .y(y)
    );

    initial clk = 0;
    always #5 clk = ~clk;

    reg [10:0] bitstream = 11'b11011011101;
    integer i;

    initial begin
        $dumpfile("dump.vcd");
        $dumpvars(0, tb_seq_detect_mealy);

        $display("time=%0t | din=%b | y=%b", $time, din, y);
        $monitor("time=%0t | din=%b | y=%b", $time, din, y);

        rst = 1;
        din = 0;
        #10;  
        rst = 0;

        for (i = 10; i >= 0; i = i - 1) begin
            din = bitstream[i];
            @(posedge clk); 
        end

        #20;
        $finish;
    end
endmodule

fsm-assignments/problem1_seqdet/dump.vcd
$date
	Tue Aug 19 00:04:14 2025
$end
$version
	Icarus Verilog
$end
$timescale
	1ns
$end
$scope module tb_seq_detect_mealy $end
$var wire 1 ! y $end
$var reg 11 " bitstream [10:0] $end
$var reg 1 # clk $end
$var reg 1 $ din $end
$var reg 1 % rst $end
$var integer 32 & i [31:0] $end
$scope module dut $end
$var wire 1 # clk $end
$var wire 1 $ din $end
$var wire 1 % rst $end
$var wire 1 ! y $end
$var parameter 2 ' init $end
$var parameter 2 ( s1 $end
$var parameter 2 ) s2 $end
$var parameter 2 * s3 $end
$var reg 2 + state_next [1:0] $end
$var reg 2 , state_present [1:0] $end
$upscope $end
$upscope $end
$enddefinitions $end
$comment Show the parameter values. $end
$dumpall
b11 *
b10 )
b1 (
b0 '
$end
#0
$dumpvars
bx ,
b0 +
bx &
1%
0$
0#
b11011011101 "
0!
$end
#5
b0 ,
1#
#10
b1 +
0#
1$
b1010 &
0%
#15
b10 +
b1 ,
b1001 &
1#
#20
0#
#25
b10 ,
b11 +
0$
b1000 &
1#
#30
0#
#35
1!
b11 ,
b1 +
1$
b111 &
1#
#40
0#
#45
b10 +
0!
b1 ,
b110 &
1#
#50
0#
#55
b10 ,
b11 +
0$
b101 &
1#
#60
0#
#65
1!
b11 ,
b1 +
1$
b100 &
1#
#70
0#
#75
b10 +
0!
b1 ,
b11 &
1#
#80
0#
#85
b10 ,
b10 &
1#
#90
0#
#95
b11 +
0$
b1 &
1#
#100
0#
#105
1!
b11 ,
b1 +
1$
b0 &
1#
#110
0#
#115
b10 +
0!
b1 ,
b11111111111111111111111111111111 &
1#
#120
0#
#125
b10 ,
1#
